golfer/__init__.py
golfer/__version__.py
golfer/dir_ast.py
golfer/golf.py
golfer/golfer.py
golfer/main.py
golfer/variable_searcher.py
golfer_py-0.2.1.dist-info/LICENSE
golfer_py-0.2.1.dist-info/METADATA
golfer_py-0.2.1.dist-info/WHEEL
golfer_py-0.2.1.dist-info/entry_points.txt
golfer_py-0.2.1.dist-info/top_level.txt
golfer_py-0.2.1.dist-info/RECORD
