Metadata-Version: 2.1
Name: golfer-py
Version: 0.2.1
Summary: Tool to shorten Python code
Author: nahco314
Author-email: nahco3_ta@yahoo.co.jp
License: MIT
Requires-Python: >=3.10
License-File: LICENSE
